cc1101/__init__.py
cc1101/_cli.py
cc1101/_gpio.py
cc1101/addresses.py
cc1101/options.py
cc1101-3.0.0.dist-info/COPYING
cc1101-3.0.0.dist-info/METADATA
cc1101-3.0.0.dist-info/WHEEL
cc1101-3.0.0.dist-info/entry_points.txt
cc1101-3.0.0.dist-info/top_level.txt
cc1101-3.0.0.dist-info/RECORD
