Metadata-Version: 2.1
Name: cc1101
Version: 3.0.0
Summary: Python Library & Command Line Tool to Transmit RF Signals via C1101 Transceivers
Home-page: https://github.com/fphammerle/python-cc1101
Author: Fabian Peter Hammerle
Author-email: fabian+python-cc1101@hammerle.me
License: GPLv3+
Project-URL: Changelog, https://github.com/fphammerle/python-cc1101/blob/master/CHANGELOG.md
Keywords: ISM,SPI,automation,radio-frequency,raspberry-pi,transceiver,transmission,wireless
Platform: UNKNOWN
Classifier: Development Status :: 4 - Beta
Classifier: Intended Audience :: Developers
Classifier: License :: OSI Approved :: GNU General Public License v3 or later (GPLv3+)
Classifier: Operating System :: POSIX :: Linux
Classifier: Programming Language :: Python :: 3.7
Classifier: Programming Language :: Python :: 3.8
Classifier: Programming Language :: Python :: 3.9
Classifier: Programming Language :: Python :: 3.10
Classifier: Programming Language :: Python :: 3.11
Classifier: Topic :: Home Automation
Classifier: Topic :: Communications
Requires-Python: >=3.7
Requires-Dist: spidev
